pycatan/__init__.py
pycatan/_development_card.py
pycatan/_game.py
pycatan/_player.py
pycatan/_resource.py
pycatan/_roll_yield.py
pycatan/board/__init__.py
pycatan/board/_beginner_board.py
pycatan/board/_board.py
pycatan/board/_board_renderer.py
pycatan/board/_building.py
pycatan/board/_building_type.py
pycatan/board/_coords.py
pycatan/board/_harbor.py
pycatan/board/_hex.py
pycatan/board/_hex_type.py
pycatan/board/_intersection.py
pycatan/board/_path.py
pycatan/board/_random_board.py
pycatan/errors.py
pycatan-1.0.1.dist-info/WHEEL
pycatan-1.0.1.dist-info/METADATA
pycatan-1.0.1.dist-info/RECORD
